bittrex_api/__bittrex_core.py
bittrex_api/__init__.py
bittrex_api/bittrex.py
bittrex_api/v1.py
bittrex_api/v2.py
bittrex_api/v3.py
bittrex_api/models/__init__.py
bittrex_api/models/v1/__init__.py
bittrex_api/models/v1/endpoints.py
bittrex_api/models/v1/keys.py
bittrex_api/models/v1/order_book_type.py
bittrex_api/models/v2/__init__.py
bittrex_api/models/v2/condition_type.py
bittrex_api/models/v2/endpoints.py
bittrex_api/models/v2/keys.py
bittrex_api/models/v2/order_type.py
bittrex_api/models/v2/tick_interval.py
bittrex_api/models/v2/time_in_effect.py
bittrex_api/models/v3/__init__.py
bittrex_api/models/v3/cancel_order_type.py
bittrex_api/models/v3/candle_interval.py
bittrex_api/models/v3/conditional_order_operand.py
bittrex_api/models/v3/deposit_status.py
bittrex_api/models/v3/endpoints.py
bittrex_api/models/v3/keys.py
bittrex_api/models/v3/order_direction.py
bittrex_api/models/v3/order_type.py
bittrex_api/models/v3/time_in_force.py
bittrex_api/models/v3/withdrawal_status.py
bittrex_api/utils/__init__.py
bittrex_api/utils/bittrex_requests.py
bittrex_api/utils/crypto.py
bittrex_api/utils/enums.py
bittrex_api/utils/strings.py
bittrex_api/utils/urls.py
bittrex_api-0.0.21.dist-info/LICENSE
bittrex_api-0.0.21.dist-info/METADATA
bittrex_api-0.0.21.dist-info/WHEEL
bittrex_api-0.0.21.dist-info/top_level.txt
bittrex_api-0.0.21.dist-info/RECORD
