Metadata-Version: 2.1
Name: bittrex-api
Version: 0.0.21
Summary: bittrex_api
Home-page: https://github.com/kkristof200/py_bittrex_api
Author: Kristof
License: UNKNOWN
Platform: UNKNOWN
Classifier: Programming Language :: Python :: 3
Classifier: License :: OSI Approved :: MIT License
Classifier: Operating System :: OS Independent
Requires-Python: >=3.5
Requires-Dist: kcu (>=0.0.61)
Requires-Dist: requests (>=2.25.1)
